PoolSeqProGen/__init__.py
PoolSeqProGen/dnaSeq.py
PoolSeqProGen/dna_seq.py
PoolSeqProGen/generate_variants.py
PoolSeqProGen/pepFasta.py
PoolSeqProGen/pep_fasta.py
PoolSeqProGen/varReads.py
PoolSeqProGen/var_reads.py
PoolSeqProGen-0.0.2.dist-info/LICENSE
PoolSeqProGen-0.0.2.dist-info/METADATA
PoolSeqProGen-0.0.2.dist-info/WHEEL
PoolSeqProGen-0.0.2.dist-info/entry_points.txt
PoolSeqProGen-0.0.2.dist-info/top_level.txt
PoolSeqProGen-0.0.2.dist-info/RECORD
