Metadata-Version: 2.1
Name: PoolSeqProGen
Version: 0.0.2
Summary: A package for creating variant protein databases for bacteria from Pool-seq experiments 
Home-page: https://github.com/RigbeGW/poolseq_variantdb
Author: Rigbe G. Weldatsadik
Author-email: rigbe.weldatsadik@helsinki.fi
License: UNKNOWN
Platform: UNKNOWN
Classifier: Programming Language :: Python :: 2
Classifier: Programming Language :: Python :: 3
Classifier: License :: OSI Approved :: Apache Software License
Classifier: Operating System :: OS Independent
Requires-Python: >=2.7,>=3.3
Requires-Dist: pyteomics
Requires-Dist: biopython
Requires-Dist: pysam
